delta_scraper/__init__.py
delta_scraper/cli.py
delta_scraper-0.1a1.dist-info/LICENSE
delta_scraper-0.1a1.dist-info/METADATA
delta_scraper-0.1a1.dist-info/WHEEL
delta_scraper-0.1a1.dist-info/entry_points.txt
delta_scraper-0.1a1.dist-info/top_level.txt
delta_scraper-0.1a1.dist-info/RECORD
