Metadata-Version: 2.1
Name: delta-scraper
Version: 0.1a1
Summary: Python library for scraping data sources and creating readable deltas
Home-page: https://github.com/simonw/delta-scraper
Author: Simon Willison
License: Apache License, Version 2.0
Platform: UNKNOWN
Classifier: Development Status :: 3 - Alpha
Classifier: Intended Audience :: Developers
Classifier: Intended Audience :: Science/Research
Classifier: Intended Audience :: End Users/Desktop
Classifier: License :: OSI Approved :: Apache Software License
Classifier: Programming Language :: Python :: 3.6
Classifier: Programming Language :: Python :: 3.7
Requires-Dist: click
Requires-Dist: requests
Requires-Dist: github-contents
Provides-Extra: test
Requires-Dist: pytest ; extra == 'test'
Requires-Dist: black ; extra == 'test'
